em_health/__init__.py
em_health/db_analyze.py
em_health/db_client.py
em_health/db_manager.py
em_health/fdw_manager.py
em_health/grafana_client.py
em_health/instruments.json
em_health/main.py
em_health/sql/init_db.sql
em_health/sql/migrations/002.sql
em_health/sql/migrations/003.sql
em_health/sql/pganalyze/create_functions.sql
em_health/sql/pganalyze/create_jobs.sql
em_health/sql/pganalyze/create_tables.sql
em_health/sql/public/create_functions.sql
em_health/sql/public/create_tables.sql
em_health/sql/public/data_counters_daily.sql
em_health/sql/public/epu_counters.sql
em_health/sql/public/epu_running_daily.sql
em_health/sql/public/epu_runs.sql
em_health/sql/public/epu_sessions.sql
em_health/sql/public/epu_state_daily.sql
em_health/sql/public/image_counters_daily.sql
em_health/sql/public/load_counters_daily.sql
em_health/sql/public/tem_off.sql
em_health/sql/public/tomo_counters.sql
em_health/sql/public/tomo_running_daily.sql
em_health/sql/public/tomo_runs.sql
em_health/sql/public/tomo_sessions.sql
em_health/sql/public/tomo_state_daily.sql
em_health/sql/public/vacuum_state_daily.sql
em_health/sql/tests/pgtap/01_schema.sql
em_health/sql/tests/pgtap/02_functions.sql
em_health/sql/tests/pgtap/03_behaviour.sql
em_health/sql/tests/pgtap/04_privileges.sql
em_health/sql/uec/create_tables.sql
em_health/tests/9999_data.xml
em_health/tests/test_app.py
em_health/tests/test_performance.py
em_health/utils/__init__.py
em_health/utils/create_task.py
em_health/utils/import_xml.py
em_health/utils/maintenance.py
em_health/utils/tools.py
em_health/utils/watcher.py
em_health-0.1a2.dist-info/licenses/LICENSE
em_health-0.1a2.dist-info/METADATA
em_health-0.1a2.dist-info/WHEEL
em_health-0.1a2.dist-info/entry_points.txt
em_health-0.1a2.dist-info/top_level.txt
em_health-0.1a2.dist-info/RECORD
