Metadata-Version: 2.4
Name: em_health
Version: 0.1a2
Summary: EMHealth is a Python package designed for continuous remote monitoring of the performance and health metrics of Thermo Fisher Scientific electron microscopes.
Author-email: Grigory Sharov <gsharov@mrc-lmb.cam.ac.uk>
License:                     GNU GENERAL PUBLIC LICENSE
Project-URL: Homepage, https://github.com/azazellochg/em_health
Project-URL: Documentation, https://em-health.readthedocs.io
Project-URL: Issues, https://github.com/azazellochg/em_health/issues
Keywords: microscope,health monitoring,TEM,SEM
Classifier: Development Status :: 4 - Beta
Classifier: License :: OSI Approved :: GNU General Public License v3 (GPLv3)
Classifier: Programming Language :: Python :: 3
Classifier: Operating System :: POSIX :: Linux
Requires-Python: <3.13
License-File: LICENSE
Requires-Dist: psycopg[binary]
Requires-Dist: watchdog
Requires-Dist: python-dotenv
Requires-Dist: requests
Provides-Extra: dev
Requires-Dist: mypy; extra == "dev"
Requires-Dist: memory-profiler; extra == "dev"
Requires-Dist: pandas; extra == "dev"
Dynamic: license-file
